app/__init__.py
app/constants.py
app/generator.py
app/main.py
app/classes/__init__.py
app/classes/stop_sheet.py
stopcli-0.0.2.dist-info/METADATA
stopcli-0.0.2.dist-info/WHEEL
stopcli-0.0.2.dist-info/entry_points.txt
stopcli-0.0.2.dist-info/top_level.txt
stopcli-0.0.2.dist-info/RECORD
